danbooru/__init__.py
danbooru/client.py
danbooru/error.py
danbooru/http.py
danbooru_py-1.0.0.dist-info/METADATA
danbooru_py-1.0.0.dist-info/WHEEL
danbooru_py-1.0.0.dist-info/top_level.txt
danbooru_py-1.0.0.dist-info/RECORD
