Metadata-Version: 2.1
Name: danbooru-py
Version: 1.0.0
Summary: 단보루 크롤링 라이브러리
Home-page: https://github.com/Tanukixi/Danbooru/tree/main/SDK
Author: VoidAsMad
Author-email: voidasmad@gmail.com
License: MIT
Platform: UNKNOWN
Requires-Python: >=3.6
